register_array/register_array.sv
/*
    this is an implementation of the register-array verilog pseudocode proposed by Huang 2014
    Paper
*/

module register_array #(
    parameter QUEUE_SIZE = 4,  // Define the size of the queue
    parameter DATA_WIDTH = 32   // Define the width of the data
) (
    input  logic                  clk,        // Clock signal
    input  logic                  rst,        // Reset signal
    input  logic                  replace,    // Signal to indicate replacement
    input  logic [DATA_WIDTH-1:0] new_entry,  // New entry to be inserted
    output logic [DATA_WIDTH-1:0] max_entry   // Output the maximum entry
);

  localparam pair_count = (QUEUE_SIZE + 1) / 2;  // Calculate the number of pairs

  logic [DATA_WIDTH-1:0] register[0:QUEUE_SIZE-1];  // Array to hold the register values

  logic [DATA_WIDTH-1:0] tmp_register[0:QUEUE_SIZE-1];  // Temporary register array

  logic [DATA_WIDTH-1:0] max[0:((QUEUE_SIZE + 1)/2)-1];  // Adjusted size for max array
  logic [DATA_WIDTH-1:0] min[0:((QUEUE_SIZE + 1)/2)-1];  // Adjusted size for min array

  always_ff @(posedge clk) begin
    if (rst) begin
      for (int j = 0; j < QUEUE_SIZE; j++) begin
        register[j] <= (j + 1) * 10;  // Initialize tree entries to some values
      end
    end else begin
      for (int i = 0; i < QUEUE_SIZE; i++) begin
        register[i] <= tmp_register[i];  // Update the register with temporary register values
      end
      if (replace) begin
        register[0] <= new_entry;
      end
    end
  end

  always_comb begin
    // Copy register values to temporary register
    for (int i = 0; i < QUEUE_SIZE; i++) begin
      tmp_register[i] = register[i];
    end

    // Calculate max and min for pairs
    for (int i = 0; i < pair_count; i++) begin
      if ((2 * i + 1) < QUEUE_SIZE) begin
        max[i] = (register[2*i] > register[2*i+1]) ? register[2*i] : register[2*i+1];
        min[i] = (register[2*i] < register[2*i+1]) ? register[2*i] : register[2*i+1];
      end else begin
        max[i] = register[2*i];  // Only one element left
        min[i] = register[2*i];  // Only one element left
      end
    end

    // Update temporary register with min/max
    for (int i = 1; i < pair_count; i++) begin
      tmp_register[2*i-1] = (min[i-1] > max[i]) ? min[i-1] : max[i];
      tmp_register[2*i]   = (min[i-1] < max[i]) ? min[i-1] : max[i];
    end

    tmp_register[0] = max[0];

  end

  assign max_entry = register[0];

endmodule

register_array/register_array_tb.sv
module register_array_tb;

  parameter TREE_DEPTH = 4;
  parameter QUEUE_SIZE = (1 << TREE_DEPTH) - 1;
  parameter DATA_WIDTH = 32;

  reg clk;
  reg rst;
  reg replace;
  reg [DATA_WIDTH-1:0] new_item;
  wire [DATA_WIDTH-1:0] top_item;

  // Reference model: array to hold the items
  reg [DATA_WIDTH-1:0] ref_items[0:QUEUE_SIZE-1];
  int ref_count;
  reg [DATA_WIDTH-1:0] expected_top_item;

  register_array #(
      .QUEUE_SIZE(QUEUE_SIZE),
      .DATA_WIDTH(DATA_WIDTH)
  ) dut (
      .clk(clk),
      .rst(rst),
      .replace(replace),
      .new_entry(new_item),
      .max_entry(top_item)
  );

  // Clock generation
  always #5 clk <= ~clk;

  // Function to find the expected top item from the reference model
  function [DATA_WIDTH-1:0] get_expected_top_item;
    integer i;
    reg [DATA_WIDTH-1:0] max_value;
    begin
      if (ref_count == 0) begin
        get_expected_top_item = '0;  // If no items, return zero
      end else begin
        max_value = ref_items[0];
        for (i = 1; i < ref_count; i = i + 1) begin
          if (ref_items[i] > max_value) begin
            max_value = ref_items[i];
          end
        end
        get_expected_top_item = max_value;
      end
    end
  endfunction

  // Test Simulation
  initial begin
    // Initialize signals
    clk = 0;
    rst = 1;
    replace = 0;
    new_item = 0;

    // Initialize reference model with the same values as the DUT
    ref_count = (1 << TREE_DEPTH) - 1;
    for (int j = 0; j < ref_count; j++) begin
      ref_items[j] = (j + 1) * 10;
    end

    // Finish reset
    repeat (2) @(posedge clk);
    rst = 0;
    repeat (6) @(posedge clk);

    // Initial assertion to check the top item after reset
    expected_top_item = get_expected_top_item();
    repeat (2) @(posedge clk);
    // Assert the top item matches expected after reset
    assert (top_item == expected_top_item)
    else
      $error(
          "Assertion failed after reset: Expected top_item = %0d, got %0d",
          expected_top_item,
          top_item
      );

    // Test case: Replace items with random values
    for (int i = 0; i < 10; i++) begin
      replace  = 1;
      new_item = $urandom_range(1, 100);
      @(posedge clk);
      replace = 0;
      @(posedge clk);

      // Update reference model
      // Replace the top item in the reference model with the new item
      for (int k = 0; k < ref_count; k++) begin
        if (ref_items[k] == expected_top_item) begin
          ref_items[k] = new_item;
          break;
        end
      end

      // Get expected top item from reference model
      expected_top_item = get_expected_top_item();
      repeat (2) @(posedge clk);
      // Assert the top item matches expected
      assert (top_item == expected_top_item)
      else
        $error(
            "Assertion failed at iteration %0d: Expected top_item = %0d, got %0d",
            i,
            expected_top_item,
            top_item
        );
      repeat (2) @(posedge clk);
    end

    // Finish simulation
    repeat (2) @(posedge clk);
    $finish;
  end

  // Monitor top item
  always @(posedge clk) begin
    if (replace) begin
      $display("Replaced top item with %0d, New top item is %0d", new_item, top_item);
    end
  end
endmodule

register_array/vivado_register_array/vivado_register_array.sim/sim_1/behav/xsim/register_array_tb.vcd
$date
   Mon Sep  9 17:39:29 2024
$end

$version
  2024.1
  $dumpfile ("register_array_tb.vcd") 
$end

$timescale
  1ps
$end

$scope module register_array_tb $end
$var reg 1 ! clk $end
$var reg 32 " new_entry [31:0] $end
$var reg 32 # max_entry [31:0] $end
$var reg 1 $ replace $end
$scope module uut $end
$var wire 1 % clk $end
$var wire 1 & replace $end
$var wire 32 ' new_entry [31:0] $end
$var reg 32 # max_entry [31:0] $end
$scope begin Block25_1 $end
$var reg 32 ( i [31:0] $end
$upscope $end
$scope begin Block32_3 $end
$var reg 32 ) i [31:0] $end
$upscope $end
$scope begin Block43_4 $end
$var reg 32 * i [31:0] $end
$upscope $end
$scope begin Block48_5 $end
$var reg 32 + i [31:0] $end
$upscope $end
$scope begin Block58_7 $end
$var reg 32 , i [31:0] $end
$upscope $end
$upscope $end
$scope begin Block43_10 $end
$var reg 32 - i [31:0] $end
$upscope $end
$upscope $end
$enddefinitions $end

#0
$dumpvars
0!
b0 "
b10110 #
0$
0%
0&
b0 '
b1000 (
b1000 )
b100 *
b100 +
b0 ,
b0 -
$end

#5000
1!
1%
b1000 )
b100 *
b100 +
b1000 ,

#10000
0!
0%

#15000
1!
b110001 #
1%
b1000 )
b100 *
b100 +
b1000 ,

#20000
0!
0%

#25000
1!
b1001100 #
1%
b1000 )
b100 *
b100 +
b1000 ,

#30000
0!
0%

#35000
1!
b1011000 #
1%
b1000 )
b100 *
b100 +
b1000 ,

#40000
0!
0%

#45000
1!
1%
b1000 )
b100 *
b100 +
b1000 ,

#50000
0!
0%

#55000
1!
1%
b1000 )
b100 *
b100 +
b1000 ,

#60000
0!
0%

#65000
1!
1%
b1000 )
b100 *
b100 +
b1000 ,

#70000
0!
0%

#75000
1!
1%
b1000 )
b100 *
b100 +
b1000 ,
b1 -

#80000
0!
0%

#85000
1!
b1010 "
1$
1%
1&
b1010 '
b1000 )
b100 *
b100 +
b1000 ,

#90000
0!
0%

#95000
1!
b1001100 #
0$
1%
0&
b1000 )
b100 *
b100 +
b1000 ,

#100000
0!
0%

#105000
1!
1%
b1000 )
b100 *
b100 +
b1000 ,

#110000
0!
0%

#115000
1!
1%
b1000 )
b100 *
b100 +
b1000 ,
b10 -

#120000
0!
0%

#125000
1!
b10100 "
1$
1%
1&
b10100 '
b1000 )
b100 *
b100 +
b1000 ,

#130000
0!
0%

#135000
1!
b1001011 #
0$
1%
0&
b1000 )
b100 *
b100 +
b1000 ,

#140000
0!
0%

#145000
1!
1%
b1000 )
b100 *
b100 +
b1000 ,

#150000
0!
0%

#155000
1!
1%
b1000 )
b100 *
b100 +
b1000 ,
b11 -

#160000
0!
0%

#165000
1!
b11110 "
1$
1%
1&
b11110 '
b1000 )
b100 *
b100 +
b1000 ,

#170000
0!
0%

#175000
1!
b111111 #
0$
1%
0&
b1000 )
b100 *
b100 +
b1000 ,

#180000
0!
0%

#185000
1!
1%
b1000 )
b100 *
b100 +
b1000 ,

#190000
0!
0%

#195000
1!
1%
b1000 )
b100 *
b100 +
b1000 ,
b100 -

#200000
0!
0%

#205000
1!
b101000 "
1$
1%
1&
b101000 '
b1000 )
b100 *
b100 +
b1000 ,

#210000
0!
0%

#215000
1!
b110001 #
0$
1%
0&
b1000 )
b100 *
b100 +
b1000 ,

#220000
0!
0%

#225000
1!
1%
b1000 )
b100 *
b100 +
b1000 ,

#230000
0!
0%

#235000
1!
1%
b1000 )
b100 *
b100 +
b1000 ,
b101 -

#240000
0!
0%

#245000
1!
1%
b1000 )
b100 *
b100 +
b1000 ,

